{
    "correlationId": "685e37f",
    "title": "Service Unavailable",
    "type": "https://api.weather.gov/problems/ServiceUnavailable",
    "status": 503,
    "detail": "An upstream data source is temporarily unavailable. Please try again later.",
    "instance": "https://api.weather.gov/requests/685e37f"
}{
    "correlationId": "685f344",
    "title": "Service Unavailable",
    "type": "https://api.weather.gov/problems/ServiceUnavailable",
    "status": 503,
    "detail": "An upstream data source is temporarily unavailable. Please try again later.",
    "instance": "https://api.weather.gov/requests/685f344"
}{
    "correlationId": "6860848",
    "title": "Service Unavailable",
    "type": "https://api.weather.gov/problems/ServiceUnavailable",
    "status": 503,
    "detail": "An upstream data source is temporarily unavailable. Please try again later.",
    "instance": "https://api.weather.gov/requests/6860848"
}{
    "correlationId": "68616cf",
    "title": "Service Unavailable",
    "type": "https://api.weather.gov/problems/ServiceUnavailable",
    "status": 503,
    "detail": "An upstream data source is temporarily unavailable. Please try again later.",
    "instance": "https://api.weather.gov/requests/68616cf"
}{
    "correlationId": "6d0868a",
    "title": "Service Unavailable",
    "type": "https://api.weather.gov/problems/ServiceUnavailable",
    "status": 503,
    "detail": "An upstream data source is temporarily unavailable. Please try again later.",
    "instance": "https://api.weather.gov/requests/6d0868a"
}{
    "correlationId": "6d11cf9",
    "title": "Service Unavailable",
    "type": "https://api.weather.gov/problems/ServiceUnavailable",
    "status": 503,
    "detail": "An upstream data source is temporarily unavailable. Please try again later.",
    "instance": "https://api.weather.gov/requests/6d11cf9"
}