{
    "correlationId": "1afa54fc",
    "title": "Service Unavailable",
    "type": "https://api.weather.gov/problems/ServiceUnavailable",
    "status": 503,
    "detail": "An upstream data source is temporarily unavailable. Please try again later.",
    "instance": "https://api.weather.gov/requests/1afa54fc"
}{
    "correlationId": "1afa824f",
    "title": "Service Unavailable",
    "type": "https://api.weather.gov/problems/ServiceUnavailable",
    "status": 503,
    "detail": "An upstream data source is temporarily unavailable. Please try again later.",
    "instance": "https://api.weather.gov/requests/1afa824f"
}{
    "correlationId": "1afa8c53",
    "title": "Service Unavailable",
    "type": "https://api.weather.gov/problems/ServiceUnavailable",
    "status": 503,
    "detail": "An upstream data source is temporarily unavailable. Please try again later.",
    "instance": "https://api.weather.gov/requests/1afa8c53"
}{
    "correlationId": "1afaa054",
    "title": "Service Unavailable",
    "type": "https://api.weather.gov/problems/ServiceUnavailable",
    "status": 503,
    "detail": "An upstream data source is temporarily unavailable. Please try again later.",
    "instance": "https://api.weather.gov/requests/1afaa054"
}{
    "correlationId": "1bdcb11c",
    "title": "Service Unavailable",
    "type": "https://api.weather.gov/problems/ServiceUnavailable",
    "status": 503,
    "detail": "An upstream data source is temporarily unavailable. Please try again later.",
    "instance": "https://api.weather.gov/requests/1bdcb11c"
}{
    "correlationId": "1afaef39",
    "title": "Service Unavailable",
    "type": "https://api.weather.gov/problems/ServiceUnavailable",
    "status": 503,
    "detail": "An upstream data source is temporarily unavailable. Please try again later.",
    "instance": "https://api.weather.gov/requests/1afaef39"
}