{
    "correlationId": "2a87443a",
    "title": "Unexpected Problem",
    "type": "https://api.weather.gov/problems/UnexpectedProblem",
    "status": 500,
    "detail": "An unexpected problem has occurred.",
    "instance": "https://api.weather.gov/requests/2a87443a"
}{
    "correlationId": "2a873cb2",
    "title": "Unexpected Problem",
    "type": "https://api.weather.gov/problems/UnexpectedProblem",
    "status": 500,
    "detail": "An unexpected problem has occurred.",
    "instance": "https://api.weather.gov/requests/2a873cb2"
}{
    "correlationId": "2a876513",
    "title": "Unexpected Problem",
    "type": "https://api.weather.gov/problems/UnexpectedProblem",
    "status": 500,
    "detail": "An unexpected problem has occurred.",
    "instance": "https://api.weather.gov/requests/2a876513"
}{
    "correlationId": "2a8786b6",
    "title": "Unexpected Problem",
    "type": "https://api.weather.gov/problems/UnexpectedProblem",
    "status": 500,
    "detail": "An unexpected problem has occurred.",
    "instance": "https://api.weather.gov/requests/2a8786b6"
}{
    "correlationId": "2faa7fee",
    "title": "Unexpected Problem",
    "type": "https://api.weather.gov/problems/UnexpectedProblem",
    "status": 500,
    "detail": "An unexpected problem has occurred.",
    "instance": "https://api.weather.gov/requests/2faa7fee"
}{
    "correlationId": "2a884f7c",
    "title": "Unexpected Problem",
    "type": "https://api.weather.gov/problems/UnexpectedProblem",
    "status": 500,
    "detail": "An unexpected problem has occurred.",
    "instance": "https://api.weather.gov/requests/2a884f7c"
}