{
    "correlationId": "3c650de",
    "title": "Unexpected Problem",
    "type": "https://api.weather.gov/problems/UnexpectedProblem",
    "status": 500,
    "detail": "An unexpected problem has occurred. If this error continues, please contact support at nco.ops@noaa.gov.",
    "instance": "https://api.weather.gov/requests/3c650de"
}{
    "correlationId": "3c66db5",
    "title": "Unexpected Problem",
    "type": "https://api.weather.gov/problems/UnexpectedProblem",
    "status": 500,
    "detail": "An unexpected problem has occurred. If this error continues, please contact support at nco.ops@noaa.gov.",
    "instance": "https://api.weather.gov/requests/3c66db5"
}{
    "correlationId": "60348ec8",
    "title": "Unexpected Problem",
    "type": "https://api.weather.gov/problems/UnexpectedProblem",
    "status": 500,
    "detail": "An unexpected problem has occurred. If this error continues, please contact support at nco.ops@noaa.gov.",
    "instance": "https://api.weather.gov/requests/60348ec8"
}{
    "correlationId": "22bec257",
    "title": "Unexpected Problem",
    "type": "https://api.weather.gov/problems/UnexpectedProblem",
    "status": 500,
    "detail": "An unexpected problem has occurred. If this error continues, please contact support at nco.ops@noaa.gov.",
    "instance": "https://api.weather.gov/requests/22bec257"
}{
    "correlationId": "736fe048",
    "title": "Unexpected Problem",
    "type": "https://api.weather.gov/problems/UnexpectedProblem",
    "status": 500,
    "detail": "An unexpected problem has occurred. If this error continues, please contact support at nco.ops@noaa.gov.",
    "instance": "https://api.weather.gov/requests/736fe048"
}{
    "correlationId": "7369be3f",
    "title": "Unexpected Problem",
    "type": "https://api.weather.gov/problems/UnexpectedProblem",
    "status": 500,
    "detail": "An unexpected problem has occurred. If this error continues, please contact support at nco.ops@noaa.gov.",
    "instance": "https://api.weather.gov/requests/7369be3f"
}